{
  "generated_at": "2026-06-24T04:36:00+00:00",
  "items": [
    {
      "id": "CR-141",
      "title": "Red Baseline Debt Triage and Closure",
      "status": "active-phase0-baseline-ready",
      "kind": "requirement-change",
      "lifecycle_status": "active",
      "readiness_status": "not_ready",
      "gate_status": "cp2_pending",
      "gate_profile": "standard",
      "source_tracking": "process/changes/CR-140-FOLLOW-UP-TRACKING-2026-06-30.md#FU-CR140-003",
      "formal_cr_path": "process/changes/CR-141-RED-BASELINE-DEBT-TRIAGE-2026-06-30.md",
      "parent_cr": "CR-140",
      "source_decision_id": "USER-20260630-CONTINUE-EXPERIMENT-REMEDIATION",
      "current_requirement_baseline_path": "process/baseline/CURRENT-REQUIREMENT-BASELINE.yaml",
      "priority": 1,
      "blocked_by": [],
      "impact_surface": [
        "46_phase0_baseline_failures",
        "tests/test_script_entrypoint_naming.py",
        "tests/test_market_data_contracts.py",
        "tests/test_experiment_17_21_factor_suite.py",
        "tests/test_experiment_23_29_ml_factor_suite.py",
        "CR139_debt",
        "redesign_intermediate_debt"
      ],
      "conflict_keys": [
        "red-baseline-debt",
        "cr139-root-script-naming-debt",
        "market-data-engine-import-boundary",
        "remaining-experiment-suite-failures"
      ],
      "authz_policy_refs": [
        "NO_CREDENTIAL_READ",
        "NO_RUNTIME",
        "NO_NAS",
        "NO_TRADING",
        "NO_PROVIDER_FETCH",
        "NO_REAL_LAKE_LINK_OR_MOUNT",
        "NO_LAKE_WRITE",
        "NO_CATALOG_POINTER_WRITE",
        "NO_REMOTE_WRITE"
      ],
      "next_gate": "phase0_baseline",
      "next_action": "Freeze CR141 red baseline, classify the 46 known pytest failures, fix only low-risk non-runtime debt, and defer remaining experiment engine convergence to FU-CR140-002.",
      "last_checked_at": "2026-06-30T17:35:00+08:00"
    },
    {
      "authz_policy_refs": [
        "NO_CREDENTIAL_READ",
        "NO_RUNTIME",
        "NO_NAS",
        "NO_TRADING",
        "NO_REMOTE_WRITE"
      ],
      "conflict_keys": [
        "state-v2",
        "process-retention-policy",
        "read-policy",
        "state-md-legacy-summary"
      ],
      "cr_type": "process",
      "full_ref": "process/changes/CR-127-STATE-V2-PROCESS-RETENTION-POLICY-2026-06-23.md",
      "gate_profile": "compact",
      "gate_status": "closed",
      "id": "CR-127",
      "impact_surface": [
        "process/state",
        "process/policies",
        "process/context",
        "process/STATE.md",
        "cr-tracking"
      ],
      "readiness": "ready",
      "risk_refs": [
        "WARN-CR137-CR-TRACKING"
      ],
      "status": "closed",
      "summary_ref": "process/changes/summaries/CR-127.summary.json",
      "title": "State v2 / Process Retention Policy Landing"
    },
    {
      "authz_policy_refs": [
        "NO_CREDENTIAL_READ",
        "NO_RUNTIME",
        "NO_NAS",
        "NO_TRADING",
        "NO_REMOTE_WRITE",
        "NO_PROVIDER_LAKE_CATALOG"
      ],
      "conflict_keys": [
        "runner-core",
        "strategy-runner",
        "offline-runner",
        "feature-doc-governance"
      ],
      "cr_type": "feature",
      "full_ref": "process/changes/CR-128-RUNNER-CORE-MVP-IMPLEMENTATION-2026-06-23.md",
      "gate_profile": "standard",
      "gate_status": "closed",
      "id": "CR-128",
      "impact_surface": [
        "trading/strategy_runner",
        "scripts/check_cr091_strategy_runner_package.py",
        "tests",
        "process/docs/features",
        "process/checks",
        "process/context"
      ],
      "readiness": "ready",
      "risk_refs": [],
      "status": "closed",
      "summary_ref": "process/changes/summaries/CR-128.summary.json",
      "title": "Runner Core MVP Implementation"
    },
    {
      "authz_policy_refs": [
        "NO_CREDENTIAL_READ",
        "NO_RUNTIME",
        "NO_NAS",
        "NO_TRADING",
        "NO_REMOTE_WRITE",
        "NO_PROVIDER_LAKE_CATALOG"
      ],
      "conflict_keys": [
        "strategy-runner-core-authority",
        "feature-doc-boundary",
        "cr102-cr103-cr104-default-feature-surface"
      ],
      "cr_type": "process",
      "full_ref": "process/changes/CR-129-FEATURE-BOUNDARY-DEDUP-STRATEGY-RUNNER-CORE-AUTHORITY-2026-06-23.md",
      "gate_profile": "compact",
      "gate_status": "closed",
      "id": "CR-129",
      "impact_surface": [
        "process/docs/features",
        "scripts",
        "tests",
        "process/checks",
        "process/context"
      ],
      "readiness": "ready",
      "risk_refs": [],
      "status": "closed",
      "summary_ref": "process/changes/summaries/CR-129.summary.json",
      "title": "Feature Boundary Dedup: Strategy Runner Core Authority"
    },
    {
      "authz_policy_refs": [
        "NO_CREDENTIAL_READ",
        "NO_RUNTIME",
        "NO_NAS",
        "NO_TRADING",
        "NO_REMOTE_WRITE",
        "NO_PROVIDER_LAKE_CATALOG"
      ],
      "conflict_keys": [
        "runner-architecture-authority",
        "design-doc-boundary",
        "cr046-legacy-cross-target",
        "cr126-runner-source-design"
      ],
      "cr_type": "process",
      "full_ref": "process/changes/CR-130-DESIGN-BOUNDARY-DEDUP-RUNNER-ARCHITECTURE-AUTHORITY-2026-06-23.md",
      "gate_profile": "compact",
      "gate_status": "closed",
      "id": "CR-130",
      "impact_surface": [
        "process/docs/design",
        "scripts",
        "tests",
        "process/checks",
        "process/context"
      ],
      "readiness": "ready",
      "risk_refs": [],
      "status": "closed",
      "summary_ref": "process/changes/summaries/CR-130.summary.json",
      "title": "Design Boundary Dedup: Runner Architecture Authority"
    },
    {
      "authz_policy_refs": [
        "NO_CREDENTIAL_READ",
        "NO_RUNTIME",
        "NO_NAS",
        "NO_TRADING",
        "NO_REMOTE_WRITE",
        "NO_PROVIDER_LAKE_CATALOG"
      ],
      "conflict_keys": [
        "design-surface-cleanup",
        "cr-named-design-archive",
        "design-root-current-authority"
      ],
      "cr_type": "process",
      "full_ref": "process/changes/CR-131-DESIGN-SURFACE-ARCHIVE-CLEANUP-2026-06-23.md",
      "gate_profile": "compact",
      "gate_status": "closed",
      "id": "CR-131",
      "impact_surface": [
        "process/docs/design",
        "process/archive/design-cr-docs",
        "scripts",
        "tests",
        "process/checks",
        "process/context"
      ],
      "readiness": "ready",
      "risk_refs": [],
      "status": "closed",
      "summary_ref": "process/changes/summaries/CR-131.summary.json",
      "title": "Design Surface Archive Cleanup"
    },
    {
      "authz_policy_refs": [
        "NO_CREDENTIAL_READ",
        "NO_RUNTIME",
        "NO_NAS",
        "NO_TRADING",
        "NO_PROVIDER_LAKE_CATALOG"
      ],
      "conflict_keys": [
        "process-artifact-hygiene",
        "runner-development-gate",
        "workspace-residual-classification"
      ],
      "cr_type": "process",
      "full_ref": "process/changes/CR-132-RESIDUAL-PROCESS-ARTIFACT-HYGIENE-2026-06-23.md",
      "gate_profile": "compact",
      "gate_status": "closed",
      "id": "CR-132",
      "impact_surface": [
        "scripts",
        "tests",
        "process/checks",
        "process/context",
        "process/changes",
        "process/state"
      ],
      "readiness": "ready",
      "risk_refs": [],
      "status": "closed",
      "summary_ref": "process/changes/summaries/CR-132.summary.json",
      "title": "Residual Process Artifact Hygiene"
    },
    {
      "authz_policy_refs": [
        "NO_CREDENTIAL_READ",
        "NO_RUNTIME",
        "NO_NAS",
        "NO_TRADING",
        "NO_PROVIDER_LAKE_CATALOG"
      ],
      "conflict_keys": [
        "strategy-runner-core",
        "run-spec-file",
        "offline-runner-cli"
      ],
      "cr_type": "feature",
      "full_ref": "process/changes/CR-133-STRATEGY-RUNNER-CORE-NEXT-SLICE-2026-06-23.md",
      "gate_profile": "standard",
      "gate_status": "closed",
      "id": "CR-133",
      "impact_surface": [
        "trading/strategy_runner",
        "tests",
        "process/docs/features/strategy-runner-core",
        "process/checks",
        "process/context",
        "process/changes",
        "process/state"
      ],
      "readiness": "ready",
      "risk_refs": [],
      "status": "closed",
      "summary_ref": "process/changes/summaries/CR-133.summary.json",
      "title": "Strategy Runner Core Next Slice"
    },
    {
      "authz_policy_refs": [
        "NO_CREDENTIAL_READ",
        "NO_RUNTIME",
        "NO_NAS",
        "NO_TRADING",
        "NO_PROVIDER_LAKE_CATALOG"
      ],
      "conflict_keys": [
        "strategy-runner-core",
        "runner-evidence-index",
        "offline-runner-cli"
      ],
      "cr_type": "feature",
      "full_ref": "process/changes/CR-134-RUNNER-EVIDENCE-INDEX-INTEGRATION-2026-06-23.md",
      "gate_profile": "standard",
      "gate_status": "closed",
      "id": "CR-134",
      "impact_surface": [
        "trading/strategy_runner",
        "tests",
        "process/docs/features/strategy-runner-core",
        "process/checks",
        "process/context",
        "process/changes",
        "process/state"
      ],
      "readiness": "ready",
      "risk_refs": [],
      "status": "closed",
      "summary_ref": "process/changes/summaries/CR-134.summary.json",
      "title": "Runner Evidence Index Integration"
    },
    {
      "authz_policy_refs": [
        "NO_CREDENTIAL_READ",
        "NO_RUNTIME",
        "NO_NAS",
        "NO_TRADING",
        "NO_PROVIDER_LAKE_CATALOG"
      ],
      "conflict_keys": [
        "strategy-runner-core",
        "runner-artifact-bundle",
        "runner-replay-inspect",
        "offline-runner-cli"
      ],
      "cr_type": "feature",
      "full_ref": "process/changes/CR-135-RUNNER-EXECUTION-ARTIFACT-BUNDLE-REPLAY-WORKFLOW-2026-06-23.md",
      "gate_profile": "standard",
      "gate_status": "closed",
      "id": "CR-135",
      "impact_surface": [
        "trading/strategy_runner",
        "tests",
        "process/docs/features/strategy-runner-core",
        "process/checks",
        "process/context",
        "process/changes",
        "process/state"
      ],
      "readiness": "ready_with_risk",
      "risk_refs": [
        "WARN-CR135-CR-TRACKING"
      ],
      "status": "closed",
      "summary_ref": "process/changes/summaries/CR-135.summary.json",
      "title": "Runner Execution Artifact Bundle / Replay Workflow"
    },
    {
      "authz_policy_refs": [
        "NO_CREDENTIAL_READ",
        "NO_RUNTIME",
        "NO_NAS",
        "NO_TRADING",
        "NO_PROVIDER_LAKE_CATALOG"
      ],
      "conflict_keys": [
        "strategy-runner-core",
        "runner-artifact-bundle",
        "runner-bundle-validation",
        "offline-runner-cli"
      ],
      "cr_type": "feature",
      "full_ref": "process/changes/CR-136-RUNNER-BUNDLE-SCHEMA-COMPATIBILITY-VALIDATION-2026-06-23.md",
      "gate_profile": "standard",
      "gate_status": "closed",
      "id": "CR-136",
      "impact_surface": [
        "trading/strategy_runner",
        "tests",
        "process/docs/features/strategy-runner-core",
        "process/checks",
        "process/context",
        "process/changes",
        "process/state"
      ],
      "readiness": "ready_with_risk",
      "risk_refs": [
        "WARN-CR136-CR-TRACKING"
      ],
      "status": "closed",
      "summary_ref": "process/changes/summaries/CR-136.summary.json",
      "title": "Runner Bundle Schema / Compatibility Validation"
    },
    {
      "authz_policy_refs": [
        "NO_CREDENTIAL_READ",
        "NO_RUNTIME",
        "NO_NAS",
        "NO_TRADING",
        "NO_PROVIDER_LAKE_CATALOG"
      ],
      "conflict_keys": [
        "strategy-runner-core",
        "runner-run-registry",
        "runner-artifact-bundle",
        "offline-runner-cli"
      ],
      "cr_type": "feature",
      "full_ref": "process/changes/CR-137-OFFLINE-RUNNER-RUN-REGISTRY-2026-06-23.md",
      "gate_profile": "standard",
      "gate_status": "closed",
      "id": "CR-137",
      "impact_surface": [
        "trading/strategy_runner",
        "tests",
        "process/docs/features/strategy-runner-core",
        "process/checks",
        "process/context",
        "process/changes",
        "process/state"
      ],
      "readiness": "ready_with_risk",
      "risk_refs": [],
      "status": "closed",
      "summary_ref": "process/changes/summaries/CR-137.summary.json",
      "title": "Offline Runner Run Registry"
    },
    {
      "authz_policy_refs": [
        "NO_CREDENTIAL_READ",
        "NO_RUNTIME",
        "NO_NAS",
        "NO_TRADING",
        "NO_PROVIDER_LAKE_CATALOG",
        "NO_REMOTE_WRITE"
      ],
      "conflict_keys": [
        "runner-operational-use-case",
        "qmt-gateway-operational-use-case",
        "strategy-runner-core",
        "qmt-gateway-runtime-boundary",
        "scoped_runtime_authorization"
      ],
      "cr_type": "product-scope",
      "full_ref": "process/changes/CR-138-RUNNER-QMT-GATEWAY-OPERATIONAL-USE-CASE-BASELINE-2026-06-24.md",
      "gate_profile": "standard",
      "gate_status": "closed",
      "id": "CR-138",
      "impact_surface": [
        "scripts/check_process_artifact_hygiene.py",
        "tests/test_cr132_process_artifact_hygiene.py",
        "process/USE-CASES.md",
        "process/context/CP2-CR138-RUNNER-QMT-OPERATIONAL-USE-CASE-CONTEXT.yaml",
        "process/checks/CP2-CR138-RUNNER-QMT-OPERATIONAL-USE-CASE-PRECHECK.md",
        "process/checks/CR138-USE-CASE-NORMALIZATION-AUDIT-2026-06-24.md",
        "process/checkpoints/CP2-CR138-RUNNER-QMT-OPERATIONAL-USE-CASE-REVIEW.md",
        "process/discussions/CP2-SCENARIO-DISCUSSION-LOG.md",
        "process/checks/CP2-DISCUSSION-CHECKPOINT.json",
        "process/docs/design/HLD-RUNNER-QMT-OPERATIONAL-CONTROL-PLANE.md",
        "process/docs/design/ARCHITECTURE-DECISION-RUNNER-QMT-OPERATIONAL-CONTROL-PLANE.md",
        "process/docs/design/BLUEPRINT.md",
        "process/docs/design/DOMAIN-MAP.md",
        "process/docs/design/DEPENDENCY-MAP.md",
        "process/context/CP3-CR138-RUNNER-QMT-HLD-CONTEXT.yaml",
        "process/checks/CP3-CR138-HLD-CONSISTENCY.md",
        "process/checkpoints/CP3-CR138-RUNNER-QMT-HLD-REVIEW.md",
        "process/discussions/CP3-HLD-DISCUSSION-LOG.md",
        "process/checks/CP3-DISCUSSION-CHECKPOINT.json",
        "process/checks/CR138-PROCESS-ARTIFACT-HYGIENE-GUARDRAIL-2026-06-24.md",
        "process/docs/design/FEATURE-DESIGN-MATRIX.md",
        "process/docs/features/runner-control-plane/DESIGN.md",
        "process/docs/features/runner-control-plane/TEST-PLAN.md",
        "process/docs/features/runner-control-plane/TASKS.md",
        "process/docs/features/qmt-gateway-service-layer/DESIGN.md",
        "process/docs/features/qmt-gateway-service-layer/TEST-PLAN.md",
        "process/docs/features/qmt-gateway-service-layer/TASKS.md",
        "process/STORY-BACKLOG.md",
        "process/STORY-BACKLOG-CR138.md",
        "process/STORY-STATUS.md",
        "process/STORY-STATUS-CR138.md",
        "process/DEVELOPMENT-PLAN.yaml",
        "process/DEVELOPMENT-PLAN-CR138.yaml",
        "process/checks/CP4-CR138-STORY-DAG-PARALLEL-SAFETY.md",
        "process/checks/CP4-CR138-STORY-DAG-PARALLEL-SAFETY.result.json",
        "process/stories/CR138-S01-shared-contracts-authorization-audit.md",
        "process/stories/CR138-S02-runner-plan-preflight-control.md",
        "process/stories/CR138-S03-runner-event-signal-rebalance-tracking.md",
        "process/stories/CR138-S04-runner-evidence-review-incident-lifecycle.md",
        "process/stories/CR138-S05-gateway-lifecycle-health-rest-contract.md",
        "process/stories/CR138-S06-gateway-query-calendar-commission-pnl.md",
        "process/stories/CR138-S07-gateway-subscription-order-report-recovery.md",
        "process/stories/CR138-S08-docs-fixtures-cp7-authorization-runbook.md",
        "process/stories/CR138-S01-shared-contracts-authorization-audit-LLD.md",
        "process/stories/CR138-S02-runner-plan-preflight-control-LLD.md",
        "process/stories/CR138-S03-runner-event-signal-rebalance-tracking-LLD.md",
        "process/stories/CR138-S04-runner-evidence-review-incident-lifecycle-LLD.md",
        "process/stories/CR138-S05-gateway-lifecycle-health-rest-contract-LLD.md",
        "process/stories/CR138-S06-gateway-query-calendar-commission-pnl-LLD.md",
        "process/stories/CR138-S07-gateway-subscription-order-report-recovery-LLD.md",
        "process/stories/CR138-S08-docs-fixtures-cp7-authorization-runbook-LLD.md",
        "process/checks/CP5-CR138-S01-shared-contracts-authorization-audit-LLD-IMPLEMENTABILITY.md",
        "process/checks/CP5-CR138-S02-runner-plan-preflight-control-LLD-IMPLEMENTABILITY.md",
        "process/checks/CP5-CR138-S03-runner-event-signal-rebalance-tracking-LLD-IMPLEMENTABILITY.md",
        "process/checks/CP5-CR138-S04-runner-evidence-review-incident-lifecycle-LLD-IMPLEMENTABILITY.md",
        "process/checks/CP5-CR138-S05-gateway-lifecycle-health-rest-contract-LLD-IMPLEMENTABILITY.md",
        "process/checks/CP5-CR138-S06-gateway-query-calendar-commission-pnl-LLD-IMPLEMENTABILITY.md",
        "process/checks/CP5-CR138-S07-gateway-subscription-order-report-recovery-LLD-IMPLEMENTABILITY.md",
        "process/checks/CP5-CR138-S08-docs-fixtures-cp7-authorization-runbook-LLD-IMPLEMENTABILITY.md",
        "process/checks/CP5-CR138-RUNNER-QMT-OPERATIONAL-CONTROL-LLD-BATCH.result.json",
        "process/context/CP5-CR138-RUNNER-QMT-OPERATIONAL-CONTROL-CONTEXT.yaml",
        "process/checkpoints/CP5-CR138-RUNNER-QMT-OPERATIONAL-CONTROL-LLD-BATCH.md",
        "process/checks/CP5-CR138-HUMAN-GATE-LAUNCH-MESSAGE.md",
        "process/state/CHECKPOINT-LEDGER.ndjson",
        "process/state/READ-EXPANSION-LEDGER.ndjson",
        "process/changes",
        "process/state"
      ],
      "readiness": "ready_with_risk",
      "risk_refs": [
        "RISK-CR138-RUNTIME-MISREAD",
        "RISK-CR138-RUNTIME-NOT-VERIFIED"
      ],
      "status": "closed-current-delivery",
      "summary_ref": "process/changes/summaries/CR-138.summary.json",
      "title": "Runner & QMT Gateway Operational Use-Case Baseline"
    },
    {
      "authz_policy_refs": [
        "NO_CREDENTIAL_READ",
        "NO_RUNTIME",
        "NO_NAS",
        "NO_TRADING",
        "NO_PROVIDER_FETCH",
        "NO_REAL_LAKE_LINK_OR_MOUNT",
        "NO_LAKE_WRITE",
        "NO_CATALOG_POINTER_WRITE",
        "NO_REMOTE_WRITE"
      ],
      "conflict_keys": [
        "experiments-directory-refactor",
        "research-reporting-module-location",
        "data-lake-readiness-audit-entrypoint",
        "turnover-factor-engine-adapter",
        "offline-golden-fixture"
      ],
      "cr_type": "refactor",
      "full_ref": "process/changes/CR-140-EXPERIMENTS-REFACTOR-2026-06-28.md",
      "gate_profile": "standard",
      "gate_status": "closed",
      "id": "CR-140",
      "impact_surface": [
        "experiments/run_experiment_turnover_factor.py",
        "experiments/run_data_lake_readiness_audit.py",
        "experiments/lake_input_contract.py",
        "experiments/training_snapshot_contract.py",
        "scripts/legacy/cr/cr012_limited_window_lake_repair.py",
        "experiments/reporting.py",
        "experiments/production_current_truth_rerun.py",
        "engine/research_reporting.py",
        "engine/production_current_truth_rerun.py",
        "scripts/data_lake/run_data_lake_readiness_audit.py",
        "scripts/data_lake/repair_market_data.py",
        "scripts/quality/check_script_entrypoints.py",
        "docs/components/SCRIPT-ENTRYPOINTS.md",
        "docs/components/EXPERIMENTS.md",
        "tests",
        "tests/fixtures/turnover_golden/",
        "process/context/EXPERIMENTS-REFACTOR-PLAN-2026-06-28.md"
      ],
      "last_checked_at": "2026-06-30T15:05:03+08:00",
      "next_action": "CR140 closed. Post-close risk supplement recorded; FU-CR140-001..004 are candidate-only follow-ups requiring explicit user selection/authorization.",
      "next_gate": "closed",
      "readiness": "not_ready",
      "risk_refs": [
        "RISK-CR140-CR139-STATUS-DRIFT",
        "RISK-CR140-PHASE3-LAKE-FIXTURE-EQUIVALENCE"
      ],
      "status": "closed-current-delivery",
      "summary_ref": "process/changes/summaries/CR-140.summary.json",
      "title": "experiments/ Directory Refactor and Parallel Factor Stack Reduction",
      "phase": "delivered",
      "updated_at": "2026-06-30T16:55:00+08:00",
      "evidence_refs": [
        "process/checks/CR140-PHASE3-TURNOVER-SYNTHETIC-PARITY-2026-06-30.md",
        "process/checks/CR140-PHASE3-BASELINE-COMPARISON-2026-06-30.md",
        "process/checks/CR140-PHASE5-FINAL-VALIDATION-2026-06-30.md",
        "process/checkpoints/CP8-CR140-DELIVERY-READINESS.md",
        "process/checks/CR140-POST-CLOSE-RISK-SUPPLEMENT-2026-06-30.md",
        "process/changes/CR-140-FOLLOW-UP-TRACKING-2026-06-30.md"
      ],
      "lifecycle_status": "closed",
      "readiness_status": "ready_with_risk",
      "closed_at": "2026-06-30T16:08:00+08:00"
    },
    {
      "id": "FU-CR140-001",
      "title": "Real lake readonly turnover semantic validation",
      "status": "candidate",
      "kind": "runtime-authorization",
      "lifecycle_status": "candidate",
      "readiness_status": "n/a",
      "gate_status": "not_started",
      "gate_profile": "standard",
      "source_tracking": "process/changes/CR-140-FOLLOW-UP-TRACKING-2026-06-30.md#FU-CR140-001",
      "formal_cr_path": "",
      "parent_cr": "CR-140",
      "source_decision_id": "CP8-CR140-POST-CLOSE-REVIEW",
      "current_requirement_baseline_path": "process/baseline/CURRENT-REQUIREMENT-BASELINE.yaml",
      "blocked_by": [
        "requires_explicit_user_selection",
        "requires_real_lake_readonly_authorization"
      ],
      "next_action": "Only start if the user explicitly selects real lake readonly turnover semantic validation; requires separate authorization and does not authorize lake write/catalog pointer/runtime."
    },
    {
      "id": "FU-CR140-002",
      "title": "Remaining experiments engine convergence",
      "status": "candidate",
      "kind": "requirement-change",
      "lifecycle_status": "candidate",
      "readiness_status": "n/a",
      "gate_status": "not_started",
      "gate_profile": "standard",
      "source_tracking": "process/changes/CR-140-FOLLOW-UP-TRACKING-2026-06-30.md#FU-CR140-002",
      "formal_cr_path": "",
      "parent_cr": "CR-140",
      "source_decision_id": "CP8-CR140-POST-CLOSE-REVIEW",
      "current_requirement_baseline_path": "process/baseline/CURRENT-REQUIREMENT-BASELINE.yaml",
      "blocked_by": [
        "requires_explicit_user_selection",
        "requires_engine_extension_contract_review"
      ],
      "next_action": "Only start if the user explicitly selects remaining experiment engine convergence; requires separate refactor CR."
    },
    {
      "id": "FU-CR140-003",
      "title": "Red baseline debt triage and closure",
      "status": "active",
      "kind": "requirement-change",
      "lifecycle_status": "active",
      "readiness_status": "not_ready",
      "gate_status": "cp2_pending",
      "gate_profile": "standard",
      "source_tracking": "process/changes/CR-140-FOLLOW-UP-TRACKING-2026-06-30.md#FU-CR140-003",
      "formal_cr_path": "process/changes/CR-141-RED-BASELINE-DEBT-TRIAGE-2026-06-30.md",
      "parent_cr": "CR-140",
      "source_decision_id": "USER-20260630-CONTINUE-EXPERIMENT-REMEDIATION",
      "current_requirement_baseline_path": "process/baseline/CURRENT-REQUIREMENT-BASELINE.yaml",
      "blocked_by": [
        "related_active_cr=CR-141",
        "formalized_as_CR-141"
      ],
      "next_action": "Formalized as CR-141; track execution on CR-141."
    },
    {
      "id": "FU-CR140-004",
      "title": "Local commits remote persistence gate",
      "status": "candidate",
      "kind": "requirement-change",
      "lifecycle_status": "candidate",
      "readiness_status": "n/a",
      "gate_status": "not_started",
      "gate_profile": "compact",
      "source_tracking": "process/changes/CR-140-FOLLOW-UP-TRACKING-2026-06-30.md#FU-CR140-004",
      "formal_cr_path": "",
      "parent_cr": "CR-140",
      "source_decision_id": "CP8-CR140-POST-CLOSE-REVIEW",
      "current_requirement_baseline_path": "process/baseline/CURRENT-REQUIREMENT-BASELINE.yaml",
      "blocked_by": [
        "requires_explicit_git_remote_write_authorization"
      ],
      "next_action": "Only start if the user explicitly authorizes Git remote write; this candidate records local commit loss risk and does not execute push."
    }
  ],
  "schema_version": 1,
  "updated_at": "2026-06-30T17:35:00+08:00",
  "active_crs": [
    {
      "id": "CR-141",
      "title": "Red Baseline Debt Triage and Closure",
      "status": "active-phase0-baseline-ready",
      "kind": "requirement-change",
      "lifecycle_status": "active",
      "readiness_status": "not_ready",
      "gate_status": "cp2_pending",
      "gate_profile": "standard",
      "source_tracking": "process/changes/CR-140-FOLLOW-UP-TRACKING-2026-06-30.md#FU-CR140-003",
      "formal_cr_path": "process/changes/CR-141-RED-BASELINE-DEBT-TRIAGE-2026-06-30.md",
      "parent_cr": "CR-140",
      "source_decision_id": "USER-20260630-CONTINUE-EXPERIMENT-REMEDIATION",
      "current_requirement_baseline_path": "process/baseline/CURRENT-REQUIREMENT-BASELINE.yaml",
      "priority": 1,
      "blocked_by": [],
      "impact_surface": [
        "46_phase0_baseline_failures",
        "tests/test_script_entrypoint_naming.py",
        "tests/test_market_data_contracts.py",
        "tests/test_experiment_17_21_factor_suite.py",
        "tests/test_experiment_23_29_ml_factor_suite.py",
        "CR139_debt",
        "redesign_intermediate_debt"
      ],
      "conflict_keys": [
        "red-baseline-debt",
        "cr139-root-script-naming-debt",
        "market-data-engine-import-boundary",
        "remaining-experiment-suite-failures"
      ],
      "authz_policy_refs": [
        "NO_CREDENTIAL_READ",
        "NO_RUNTIME",
        "NO_NAS",
        "NO_TRADING",
        "NO_PROVIDER_FETCH",
        "NO_REAL_LAKE_LINK_OR_MOUNT",
        "NO_LAKE_WRITE",
        "NO_CATALOG_POINTER_WRITE",
        "NO_REMOTE_WRITE"
      ],
      "next_gate": "phase0_baseline",
      "next_action": "Freeze CR141 red baseline, classify the 46 known pytest failures, fix only low-risk non-runtime debt, and defer remaining experiment engine convergence to FU-CR140-002.",
      "last_checked_at": "2026-06-30T17:35:00+08:00"
    }
  ],
  "status": "active-formal-cr"
}
