{
  "blockers": [],
  "checked_at": "2026-06-21T14:03:44+00:00",
  "checkpoint": "CP0",
  "context_ref": "process/context/CP0-CR108.context.json",
  "cr_id": "CR-108",
  "decision": "PASS",
  "dispatch_refs": [],
  "evidence_ref": "",
  "items": [
    {
      "evidence_refs": [
        "process/state/STATE.current.json",
        "process/changes/CR-INDEX.json",
        "process/context/CP0-CR108.context.json"
      ],
      "id": "CP0-BS-01",
      "name": "workspace/state/bootstrap artifacts exist",
      "severity": "INFO",
      "status": "PASS"
    },
    {
      "evidence_refs": [
        "process/changes/summaries/CR-108.summary.json"
      ],
      "id": "CP0-BS-02",
      "name": "runtime and credential actions are not authorized",
      "severity": "INFO",
      "status": "PASS"
    }
  ],
  "next_route": "human_gate",
  "schema_version": 1,
  "waivers": []
}
